toms/__init__.py
toms/__main__.py
toms/toms.py
toms-0.4.5.dist-info/LICENSE
toms-0.4.5.dist-info/METADATA
toms-0.4.5.dist-info/WHEEL
toms-0.4.5.dist-info/entry_points.txt
toms-0.4.5.dist-info/top_level.txt
toms-0.4.5.dist-info/RECORD
